{"cameraMode":{"drawMode":0,"name":"Shaded","section":"Shading Mode"},"sceneLighting":true,"audioPlay":false,"sceneViewState":{"m_AlwaysRefresh":false,"showFog":true,"showSkybox":false,"showFlares":true,"showImageEffects":true,"showParticleSystems":true,"showVisualEffectGraphs":true,"m_FxEnabled":true},"in2DMode":false,"pivot":{"x":-9.024988174438477,"y":-4.818983554840088,"z":5.506138324737549},"rotation":{"x":-0.20356206595897675,"y":0.6773460507392883,"z":-0.20387037098407746,"w":-0.6770577430725098},"size":18.446340560913087,"orthographic":false}